DeviceServer/__init__.py
DeviceServer/api_client.py
DeviceServer/api_response.py
DeviceServer/configuration.py
DeviceServer/exceptions.py
DeviceServer/py.typed
DeviceServer/rest.py
DeviceServer/api/__init__.py
DeviceServer/api/attenuator_api.py
DeviceServer/api/device_mount_system_api.py
DeviceServer/api/devices_api.py
DeviceServer/api/docker_api.py
DeviceServer/api/internal_api.py
DeviceServer/api/serial_mux_api.py
DeviceServer/api/turntable_api.py
DeviceServer/models/__init__.py
DeviceServer/models/attenuation_state.py
DeviceServer/models/channel_attenuation_state.py
DeviceServer/models/db_button_state.py
DeviceServer/models/db_device_button.py
DeviceServer/models/db_device_led.py
DeviceServer/models/db_device_port.py
DeviceServer/models/db_device_temperature_port.py
DeviceServer/models/db_led_state.py
DeviceServer/models/db_port_state.py
DeviceServer/models/db_upload_firmware_state.py
DeviceServer/models/device.py
DeviceServer/models/device_button.py
DeviceServer/models/device_led.py
DeviceServer/models/device_port.py
DeviceServer/models/device_rx_buffer.py
DeviceServer/models/device_temperature_port.py
DeviceServer/models/device_tx_buffer.py
DeviceServer/models/firmware_version.py
DeviceServer/models/host_config.py
DeviceServer/models/led_state.py
DeviceServer/models/port_state.py
DeviceServer/models/post_verify_user_access_request.py
DeviceServer/models/put_device_device_id_description200_response.py
DeviceServer/models/put_device_device_id_name200_response.py
DeviceServer/models/relay_state.py
DeviceServer/models/temp_range.py
DeviceServer/models/temperature.py
icotest_deviceserver-1.2.6.dist-info/LICENSE
icotest_deviceserver-1.2.6.dist-info/METADATA
icotest_deviceserver-1.2.6.dist-info/WHEEL
icotest_deviceserver-1.2.6.dist-info/top_level.txt
icotest_deviceserver-1.2.6.dist-info/RECORD
