Metadata-Version: 2.1
Name: Icotest-DeviceServer
Version: 1.2.6
Summary: Icotest Device Server API
Home-page: 
Author: David Atkins
Author-email: Gustav Rodel <gustav.rodel@3adesign.co.uk>, David Atkins <david@3adesign.co.uk>
License: Copyright © 2025 3ADesign Limited
Keywords: OpenAPI,OpenAPI-Generator,Icotest-Device-Server
Classifier: License :: OSI Approved :: MIT License
Classifier: Programming Language :: Python
Classifier: Programming Language :: Python :: 3
Requires-Python: >=3.4
License-File: LICENSE
Requires-Dist: connexion>=2.0.2
Requires-Dist: swagger-ui-bundle>=0.0.2
Requires-Dist: python-dateutil>=2.6.0
Requires-Dist: setuptools>=21.0.0
Requires-Dist: requests
